kepconfig/__init__.py
kepconfig/connection.py
kepconfig/error.py
kepconfig/structures.py
kepconfig/utils.py
kepconfig/admin/__init__.py
kepconfig/admin/lls.py
kepconfig/admin/ua_server.py
kepconfig/admin/user_groups.py
kepconfig/admin/users.py
kepconfig/adv_tags/__init__.py
kepconfig/adv_tags/adv_tag_group.py
kepconfig/adv_tags/average_tags.py
kepconfig/adv_tags/complex_tags.py
kepconfig/adv_tags/cumulative_tags.py
kepconfig/adv_tags/derived_tags.py
kepconfig/adv_tags/link_tags.py
kepconfig/adv_tags/max_tags.py
kepconfig/adv_tags/min_tags.py
kepconfig/connectivity/__init__.py
kepconfig/connectivity/channel.py
kepconfig/connectivity/device.py
kepconfig/connectivity/tag.py
kepconfig/connectivity/egd/__init__.py
kepconfig/connectivity/egd/exchange.py
kepconfig/connectivity/egd/name.py
kepconfig/connectivity/egd/range.py
kepconfig/connectivity/udd/__init__.py
kepconfig/connectivity/udd/profile.py
kepconfig/datalogger/__init__.py
kepconfig/datalogger/log_group.py
kepconfig/datalogger/log_items.py
kepconfig/datalogger/mapping.py
kepconfig/datalogger/triggers.py
kepconfig/iot_gateway/__init__.py
kepconfig/iot_gateway/agent.py
kepconfig/iot_gateway/iot_items.py
kepconfig/ua_gateway/__init__.py
kepconfig/ua_gateway/certificates.py
kepconfig/ua_gateway/client.py
kepconfig/ua_gateway/common.py
kepconfig/ua_gateway/server.py
kepconfig-1.4.2.dist-info/licenses/LICENSE
kepconfig-1.4.2.dist-info/METADATA
kepconfig-1.4.2.dist-info/WHEEL
kepconfig-1.4.2.dist-info/top_level.txt
kepconfig-1.4.2.dist-info/RECORD
