Metadata-Version: 2.4
Name: kepconfig
Version: 1.4.2
Summary: SDK package for Kepware Configuration API
Home-page: https://github.com/PTCInc/Kepware-ConfigAPI-SDK-Python
Author: PTC Inc
License: MIT License
Keywords: Kepware,OPC,Configuration,Thingworx
Classifier: Development Status :: 5 - Production/Stable
Classifier: License :: OSI Approved :: MIT License
Classifier: Programming Language :: Python
Classifier: Programming Language :: Python :: 3
Classifier: Programming Language :: Python :: 3.9
Classifier: Programming Language :: Python :: 3.10
Classifier: Programming Language :: Python :: 3.11
Classifier: Programming Language :: Python :: 3.12
Classifier: Programming Language :: Python :: 3.13
Classifier: Programming Language :: Python :: 3 :: Only
Classifier: Operating System :: OS Independent
Classifier: Intended Audience :: Manufacturing
Classifier: Intended Audience :: Developers
Requires-Python: >=3.9
License-File: LICENSE
Dynamic: author
Dynamic: classifier
Dynamic: description
Dynamic: description-content-type
Dynamic: home-page
Dynamic: keywords
Dynamic: license
Dynamic: license-file
Dynamic: requires-python
Dynamic: summary
